starlette_problem/__init__.py
starlette_problem/cors.py
starlette_problem/error.py
starlette_problem/handler.py
starlette_problem/py.typed
starlette_problem/schemas.py
starlette_problem/util.py
starlette_problem-0.13.0.dist-info/METADATA
starlette_problem-0.13.0.dist-info/WHEEL
starlette_problem-0.13.0.dist-info/licenses/LICENSE
starlette_problem-0.13.0.dist-info/RECORD
