Metadata-Version: 2.4
Name: starlette-problem
Version: 0.13.0
Summary: Starlette support for RFC9457 problems.
Project-URL: homepage, https://github.com/NRWLDev/starlette-problem/
Project-URL: documentation, https://nrwldev.github.io/starlette-problem/
Author-email: Daniel Edgecombe <daniel@nrwl.co>
License-Expression: Apache-2.0
License-File: LICENSE
Keywords: exception,handler,starlette,webdev
Classifier: Development Status :: 4 - Beta
Classifier: Environment :: Web Environment
Classifier: Intended Audience :: Developers
Classifier: License :: OSI Approved :: Apache Software License
Classifier: Operating System :: OS Independent
Classifier: Programming Language :: Python
Classifier: Programming Language :: Python :: 3
Classifier: Programming Language :: Python :: 3 :: Only
Classifier: Programming Language :: Python :: 3.10
Classifier: Programming Language :: Python :: 3.11
Classifier: Programming Language :: Python :: 3.12
Classifier: Topic :: Internet
Classifier: Topic :: Utilities
Requires-Python: >=3.10
Requires-Dist: rfc9457>=0.4.0
Provides-Extra: dev
Requires-Dist: changelog-gen>=0.13.8; extra == 'dev'
Requires-Dist: pre-commit>=4.5.1; extra == 'dev'
Requires-Dist: pytest-asyncio>=1.3.0; extra == 'dev'
Requires-Dist: pytest-cov>=7.0.0; extra == 'dev'
Requires-Dist: pytest-httpx>=0.36.0; extra == 'dev'
Requires-Dist: pytest-random-order>=1.2.0; extra == 'dev'
Requires-Dist: pytest>=9.0.2; extra == 'dev'
Requires-Dist: ruff>=0.14.10; extra == 'dev'
Requires-Dist: starlette; extra == 'dev'
Requires-Dist: uvicorn; extra == 'dev'
